appengine_python_standard_tbafork-1.1.5.dev1-py3.12-nspkg.pth
google/appengine/__init__.py
google/appengine/_internal/__init__.py
google/appengine/_internal/antlr3/__init__.py
google/appengine/_internal/antlr3/compat.py
google/appengine/_internal/antlr3/constants.py
google/appengine/_internal/antlr3/dfa.py
google/appengine/_internal/antlr3/dottreegen.py
google/appengine/_internal/antlr3/exceptions.py
google/appengine/_internal/antlr3/extras.py
google/appengine/_internal/antlr3/main.py
google/appengine/_internal/antlr3/recognizers.py
google/appengine/_internal/antlr3/streams.py
google/appengine/_internal/antlr3/tokens.py
google/appengine/_internal/antlr3/tree.py
google/appengine/_internal/antlr3/treewizard.py
google/appengine/api/__init__.py
google/appengine/api/api_base_pb2.py
google/appengine/api/api_testutil.py
google/appengine/api/apiproxy_rpc.py
google/appengine/api/apiproxy_stub.py
google/appengine/api/apiproxy_stub_map.py
google/appengine/api/appinfo.py
google/appengine/api/appinfo_errors.py
google/appengine/api/backendinfo.py
google/appengine/api/cmp_compat.py
google/appengine/api/croninfo.py
google/appengine/api/datastore.py
google/appengine/api/datastore_admin.py
google/appengine/api/datastore_entities.py
google/appengine/api/datastore_errors.py
google/appengine/api/datastore_file_stub.py
google/appengine/api/datastore_types.py
google/appengine/api/dispatchinfo.py
google/appengine/api/full_app_id.py
google/appengine/api/lib_config.py
google/appengine/api/mail.py
google/appengine/api/mail_errors.py
google/appengine/api/mail_service_pb2.py
google/appengine/api/mail_stub.py
google/appengine/api/mail_stub_service_pb2.py
google/appengine/api/module_testutil.py
google/appengine/api/queueinfo.py
google/appengine/api/request_info.py
google/appengine/api/stublib.py
google/appengine/api/titanoboa_request_info.py
google/appengine/api/urlfetch.py
google/appengine/api/urlfetch_errors.py
google/appengine/api/urlfetch_service_pb2.py
google/appengine/api/urlfetch_stub.py
appengine_python_standard_tbafork-1.1.5.dev1.dist-info/LICENSE
appengine_python_standard_tbafork-1.1.5.dev1.dist-info/METADATA
appengine_python_standard_tbafork-1.1.5.dev1.dist-info/WHEEL
appengine_python_standard_tbafork-1.1.5.dev1.dist-info/namespace_packages.txt
appengine_python_standard_tbafork-1.1.5.dev1.dist-info/top_level.txt
appengine_python_standard_tbafork-1.1.5.dev1.dist-info/RECORD
